{
  "data": [
    {
      "id": 1,
      "avatar": "",
      "city": "Krasnosilka",
      "post": "asasdasdasdas",
      "salary": "Yes",
      "contact": "0353431537",
      "full_name": "Tin dep trai",
      "start_date": "Male",
      "age": "22",
      "status": 1
    },
    {
      "id": 2,
      "avatar": "",
      "city": "Krasnosilka",
      "post": "asasdasdasdas",
      "salary": "Yes",
      "contact": "0353431537",
      "full_name": "Tin dep trai",
      "start_date": "Male",
      "age": "22",
      "status": 1
    },
    {
      "id": 3,
      "avatar": "",
      "experience": "1 Year",
      "post": "158 Lạc Long Quân",
      "salary": "Yes",
      "contact": "0353431537",
      "full_name": "Tin dep trai",
      "start_date": "Male",
      "age": "22",
      "status": 1
    },
    {
      "id": 3,
      "avatar": "",
      "experience": "1 Year",
      "post": "asasdasdasdas",
      "salary": "Yes",
      "contact": "0353431537",
      "full_name": "Tao la ai",
      "start_date": "Male",
      "age": "22",
      "status": 1
    },
    {
      "id": 4,
      "avatar": "",
      "post": "88 New york",
      "experience": "1 Year",
      "salary": "Yes",
      "contact": "0123456789",
      "full_name": "Pham duc toan",
      "start_date": "Male",
      "age": "22",
      "status": 1
    },
    {
      "id": 5,
      "avatar": "",
      "post": "Vinhome grandpark",
      "experience": "1 Year",
      "salary": "No",
      "contact": "0948877042",
      "full_name": "Nguyen Van Tin",
      "start_date": "Male",
      "age": "23",
      "status": 1
    },
    {
      "id": 6,
      "avatar": "",
      "post": "11 lac long quan",
      "experience": "1 Year",
      "salary": "Yes",
      "contact": "Nguyenthanhkh15@gmail.com",
      "full_name": "Nguyễn Tín",
      "start_date": "Male",
      "age": "32",
      "status": 1
    },
    {
      "id": 7,
      "avatar": "",
      "experience": "1 Year",
      "post": "qưe",
      "salary": "No",
      "contact": "qưeq",
      "full_name": "qưew",
      "start_date": "Male",
      "age": "12",
      "status": 1
    },
    {
      "id": 8,
      "avatar": "",
      "post": "123 aaa",
      "salary": "Yes",
      "experience": "1 Year",
      "contact": "0000000000",
      "full_name": "aaaaaaaaaaa",
      "start_date": "Male",
      "age": "20",
      "status": 1
    },
    {
      "id": 9,
      "avatar": "",
      "post": "69 tran hung dao",
      "salary": "Yes",
      "experience": "1 Year",
      "contact": "0123456789",
      "full_name": "Pham duc toan",
      "start_date": "Male",
      "age": "14",
      "status": 1
    },
    {
      "id": 10,
      "avatar": "",
      "post": "cơ sở dĩ an bình dương",
      "salary": "Yes",
      "experience": "1 Year",
      "contact": "0987654321",
      "full_name": "hi",
      "start_date": "Female",
      "age": "50",
      "status": 1
    }
  ]
}